odoo/addons/edi_notification_oca/README.rst
odoo/addons/edi_notification_oca/__init__.py
odoo/addons/edi_notification_oca/__manifest__.py
odoo/addons/edi_notification_oca/components/__init__.py
odoo/addons/edi_notification_oca/components/listener.py
odoo/addons/edi_notification_oca/data/mail_activity_data.xml
odoo/addons/edi_notification_oca/i18n/edi_notification_oca.pot
odoo/addons/edi_notification_oca/i18n/it.po
odoo/addons/edi_notification_oca/models/__init__.py
odoo/addons/edi_notification_oca/models/edi_exchange_record.py
odoo/addons/edi_notification_oca/models/edi_exchange_type.py
odoo/addons/edi_notification_oca/readme/CONTRIBUTORS.rst
odoo/addons/edi_notification_oca/readme/CREDITS.rst
odoo/addons/edi_notification_oca/readme/DESCRIPTION.rst
odoo/addons/edi_notification_oca/static/description/icon.png
odoo/addons/edi_notification_oca/static/description/index.html
odoo/addons/edi_notification_oca/tests/__init__.py
odoo/addons/edi_notification_oca/tests/test_edi_notification.py
odoo/addons/edi_notification_oca/views/edi_exchange_type_views.xml
odoo_addon_edi_notification_oca-16.0.1.0.0.4.dist-info/METADATA
odoo_addon_edi_notification_oca-16.0.1.0.0.4.dist-info/WHEEL
odoo_addon_edi_notification_oca-16.0.1.0.0.4.dist-info/top_level.txt
odoo_addon_edi_notification_oca-16.0.1.0.0.4.dist-info/RECORD
